Metadata-Version: 2.1
Name: gardenlinux
Version: 1.1735.0
Summary: gardenlinux CICD utils
Requires-Python: >=3.9.*
License-File: LICENSE.md
License-File: NOTICE.md
